PyIseeClub/SSHTunnel.py
PyIseeClub/__init__.py
PyIseeClub/datetime_utils.py
PyIseeClub/generate.py
PyIseeClub/generate_com.py
PyIseeClub/mysql_club.py
PyIseeClub/redis_tools.py
PyIseeClub/sqlite_func.py
PyIseeClub-0.2.7.dist-info/METADATA
PyIseeClub-0.2.7.dist-info/WHEEL
PyIseeClub-0.2.7.dist-info/top_level.txt
PyIseeClub-0.2.7.dist-info/RECORD
